LICENSE
tdf_tools/app.py
tdf_tools/pipeline.py
tdf_tools/pipelines/fix_header.py
tdf_tools/pipelines/git.py
tdf_tools/pipelines/module.py
tdf_tools/pipelines/package.py
tdf_tools/pipelines/router.py
tdf_tools/pipelines/translate.py
tdf_tools/pipelines/upgrade.py
tdf_tools/tools/cli/module_deps_rewrite.py
tdf_tools/tools/cli/project_cli.py
tdf_tools/tools/cmd.py
tdf_tools/tools/config/config.py
tdf_tools/tools/config/initial_json_config.py
tdf_tools/tools/config/module_json_config.py
tdf_tools/tools/config/packages_config.py
tdf_tools/tools/dependencies_analysis.py
tdf_tools/tools/env.py
tdf_tools/tools/fix_header/fix_header_entry.py
tdf_tools/tools/fix_header/fix_header_lint.py
tdf_tools/tools/fix_header/fix_header_lint_tool.py
tdf_tools/tools/fix_header/fix_header_replace_tool.py
tdf_tools/tools/flutter_script.py
tdf_tools/tools/gitlab/gitlab_utils.py
tdf_tools/tools/gitlab/python_gitlab_api.py
tdf_tools/tools/module/module_tools.py
tdf_tools/tools/package/seal_off_package_utils.py
tdf_tools/tools/platform_tools.py
tdf_tools/tools/print.py
tdf_tools/tools/regular_tool.py
tdf_tools/tools/shell_dir.py
tdf_tools/tools/translate/file_util.py
tdf_tools/tools/translate/flutter/flutter_translate_lint.py
tdf_tools/tools/translate/flutter/flutter_translate_tools.py
tdf_tools/tools/translate/flutter/tools/flutter_translate_integrate.py
tdf_tools/tools/translate/ios/ios_translate.py
tdf_tools/tools/translate/ios/ios_translate_lint.py
tdf_tools/tools/translate/ios/tools/batch_pod_tools.py
tdf_tools/tools/translate/ios/tools/ios_module.py
tdf_tools/tools/translate/ios/tools/ios_translate_integrate.py
tdf_tools/tools/translate/ios/tools/ios_translate_pattern.py
tdf_tools/tools/translate/ios/tools/ios_translate_tools.py
tdf_tools/tools/translate/ios/tools/location_string_temp.py
tdf_tools/tools/translate/ios/tools/podspec.py
tdf_tools/tools/translate/ios/tools/string_util.py
tdf_tools/tools/translate/tools/translate_tool.py
tdf_tools/tools/translate/translate_lint.py
tdf_tools-2.1.4.dist-info/entry_points.txt
tdf_tools-2.1.4.dist-info/LICENSE
tdf_tools-2.1.4.dist-info/WHEEL
tdf_tools-2.1.4.dist-info/METADATA
tdf_tools-2.1.4.dist-info/RECORD
