Metadata-Version: 2.1
Name: tdf-tools
Version: 2.1.4
Summary: 二维火 flutter 脚手架工具
Home-page: https://git.2dfire.net/app/flutter/tools/package_tools
License: MIT
Keywords: tdf,tdf-tools,tdf_tools
Author: Jian Xu
Author-email: 17826875951@163.com
Requires-Python: >=3.9.0,<4.0.0
Classifier: Development Status :: 4 - Beta
Classifier: Environment :: Web Environment
Classifier: Framework :: AsyncIO
Classifier: Intended Audience :: Developers
Classifier: License :: OSI Approved :: MIT License
Classifier: Operating System :: POSIX
Classifier: Programming Language :: Python
Classifier: Programming Language :: Python :: 3
Classifier: Programming Language :: Python :: 3 :: Only
Classifier: Programming Language :: Python :: 3.10
Classifier: Programming Language :: Python :: 3.9
Classifier: Topic :: Software Development
Classifier: Topic :: Software Development :: Libraries
Requires-Dist: environs (>=9.5.0,<10.0.0)
Requires-Dist: fire (>=0.4.0,<0.5.0)
Requires-Dist: googletrans (==3.1.0a0)
Requires-Dist: python-gitlab (==1.15.0)
Requires-Dist: requests (==2.27.1)
Requires-Dist: ruamel.yaml (>=0.17.21,<0.18.0)
Project-URL: Repository, https://git.2dfire.net/app/flutter/tools/package_tools.git
